gfafunctionality/__init__.py
gfafunctionality/guiqwt_plotter.py
gfafunctionality/raws.py
gfafunctionality/analysis/__init__.py
gfafunctionality/analysis/fft.py
gfafunctionality/analysis/ptc.py
gfafunctionality/analysis/raw_analysis.py
gfafunctionality-1.0.0.dist-info/LICENSE
gfafunctionality-1.0.0.dist-info/METADATA
gfafunctionality-1.0.0.dist-info/WHEEL
gfafunctionality-1.0.0.dist-info/top_level.txt
gfafunctionality-1.0.0.dist-info/RECORD
