Metadata-Version: 2.1
Name: gfafunctionality
Version: 1.0.0
Summary: UNKNOWN
Home-page: https://gitlab.pic.es/desi/gfafunctionality/tree/master
Author: David Roman
Author-email: droman@ifae.es
License: BSD-3
Platform: UNKNOWN
Classifier: Development Status :: 5 - Production/Stable
Classifier: Intended Audience :: Developers
Classifier: License :: OSI Approved :: BSD License
Classifier: Programming Language :: Python :: 3
Requires-Dist: astropy
Requires-Dist: guidata
Requires-Dist: guiqwt
Requires-Dist: matplotlib
Requires-Dist: numpy
Requires-Dist: scipy
Requires-Dist: sip
